pydeepdiff
test
