Metadata-Version: 1.0
Name: pydeepdiff
Version: 1.0.3
Summary: Computes deep differences between objects
Home-page: https://github.com/pagesjaunes/pydeepdiff
Author: PagesJaunes
Author-email: fdepaulis@pagesjaunes.fr
License: UNKNOWN
Platform: UNKNOWN
